{"add":{"path":"part-00000-265ffb28-92f0-406f-a4ca-ea0afdc8e129-c000.snappy.parquet","partitionValues":{},"size":9079,"modificationTime":1769710240920,"dataChange":true,"stats":"{\"numRecords\":62,\"minValues\":{\"expiry\":\"20260320\",\"right\":\"C\",\"timestamp\":\"2026-01-29T13:10:40.717882Z\",\"last\":-0.0,\"open_interest\":0,\"vega\":0.2711384319120995,\"volume\":0,\"yearmonth\":202603,\"date\":\"2026-01-29\",\"ask\":2.97,\"theta\":-0.09648090221001304,\"delta\":-0.7847119685700745,\"strike\":246.0,\"symbol\":\"IWM\",\"bid\":2.93,\"iv\":-0.0,\"gamma\":0.012588320714954755},\"maxValues\":{\"expiry\":\"20260320\",\"last\":17.2,\"delta\":0.7937711771232505,\"volume\":49872,\"vega\":0.38826547919985543,\"bid\":20.06,\"open_interest\":0,\"theta\":-0.032220635691025734,\"timestamp\":\"2026-01-29T13:10:40.719203Z\",\"iv\":0.0,\"yearmonth\":202603,\"gamma\":0.02047010521993416,\"symbol\":\"IWM\",\"right\":\"P\",\"strike\":278.0,\"date\":\"2026-01-29\",\"ask\":20.18},\"nullCount\":{\"date\":0,\"bid\":0,\"open_interest\":0,\"delta\":0,\"right\":0,\"expiry\":0,\"last\":0,\"iv\":0,\"gamma\":0,\"vega\":0,\"symbol\":0,\"yearmonth\":0,\"timestamp\":0,\"ask\":0,\"strike\":0,\"theta\":0,\"volume\":0}}","tags":null,"baseRowId":null,"defaultRowCommitVersion":null,"clusteringProvider":null}}
{"commitInfo":{"timestamp":1769710240920,"operation":"WRITE","operationParameters":{"mode":"Append"},"engineInfo":"delta-rs:py-1.3.2","operationMetrics":{"execution_time_ms":3,"num_added_files":1,"num_added_rows":62,"num_partitions":0,"num_removed_files":0},"clientVersion":"delta-rs.py-1.3.2"}}