{"add":{"path":"strike_partition=560/symbol=QQQ/part-00000-38fb0bf0-de2e-4264-8e3f-2bd9dad65f8e-c000.snappy.parquet","partitionValues":{"symbol":"QQQ","strike_partition":"560"},"size":5067,"modificationTime":1770237415659,"dataChange":true,"stats":"{\"numRecords\":4,\"minValues\":{\"gamma\":0.004492110585081034,\"open_interest\":0,\"iv\":0.2641890259334887,\"right\":\"CALL\",\"date\":\"2026-02-04\",\"expiry\":\"20260331\",\"theta\":-0.20944356224381977,\"bid\":8.04,\"yearmonth\":202602,\"timestamp\":\"2026-02-04T15:36:10.844324Z\",\"delta\":-0.2307926496939721,\"volume\":0,\"vega\":0.6737350999382059,\"strike\":563.0,\"ask\":8.13,\"last\":7.6},\"maxValues\":{\"theta\":-0.15255165707974783,\"timestamp\":\"2026-02-04T15:36:14.582556Z\",\"expiry\":\"20260331\",\"yearmonth\":202602,\"vega\":0.6887908674020338,\"open_interest\":0,\"right\":\"PUT\",\"bid\":54.01,\"volume\":176,\"strike\":568.0,\"date\":\"2026-02-04\",\"last\":10.35,\"iv\":0.27281852998827166,\"delta\":0.7925209458267433,\"ask\":55.43,\"gamma\":0.004865656605952127},\"nullCount\":{\"open_interest\":0,\"ask\":0,\"theta\":0,\"date\":0,\"timestamp\":0,\"bid\":0,\"right\":0,\"gamma\":0,\"last\":0,\"strike\":0,\"volume\":0,\"delta\":0,\"expiry\":0,\"vega\":0,\"yearmonth\":0,\"iv\":0}}","tags":null,"baseRowId":null,"defaultRowCommitVersion":null,"clusteringProvider":null}}
{"add":{"path":"strike_partition=600/symbol=QQQ/part-00000-afd33275-4f22-426e-bcf5-dd8e0dec5b45-c000.snappy.parquet","partitionValues":{"strike_partition":"600","symbol":"QQQ"},"size":5088,"modificationTime":1770237415659,"dataChange":true,"stats":"{\"numRecords\":4,\"minValues\":{\"ask\":18.01,\"last\":17.79,\"delta\":-0.4710213742993869,\"yearmonth\":202602,\"theta\":-0.22428466178801187,\"timestamp\":\"2026-02-04T15:36:30.390588Z\",\"volume\":13,\"right\":\"CALL\",\"strike\":603.0,\"bid\":17.9,\"open_interest\":0,\"iv\":0.2197526647833279,\"vega\":0.9231204045952985,\"date\":\"2026-02-04\",\"gamma\":0.0074371950050765275,\"expiry\":\"20260331\"},\"maxValues\":{\"ask\":25.28,\"strike\":608.0,\"date\":\"2026-02-04\",\"iv\":0.22621511448213005,\"gamma\":0.007818577752537113,\"vega\":0.9335150697418335,\"volume\":114,\"open_interest\":0,\"expiry\":\"20260331\",\"bid\":24.53,\"last\":25.0,\"yearmonth\":202602,\"delta\":0.5722263532180677,\"theta\":-0.1581466291580469,\"timestamp\":\"2026-02-04T15:36:33.956231Z\",\"right\":\"PUT\"},\"nullCount\":{\"yearmonth\":0,\"timestamp\":0,\"last\":0,\"strike\":0,\"vega\":0,\"gamma\":0,\"theta\":0,\"date\":0,\"delta\":0,\"open_interest\":0,\"expiry\":0,\"volume\":0,\"iv\":0,\"ask\":0,\"right\":0,\"bid\":0}}","tags":null,"baseRowId":null,"defaultRowCommitVersion":null,"clusteringProvider":null}}
{"add":{"path":"strike_partition=650/symbol=QQQ/part-00000-817a5d4b-39be-488e-9e30-ae7c9688b327-c000.snappy.parquet","partitionValues":{"strike_partition":"650","symbol":"QQQ"},"size":4890,"modificationTime":1770237415659,"dataChange":true,"stats":"{\"numRecords\":2,\"minValues\":{\"vega\":0.49666294696936575,\"yearmonth\":202602,\"iv\":0.1735144268606305,\"theta\":-0.10310547444825247,\"delta\":-0.8697286873792283,\"timestamp\":\"2026-02-04T15:36:54.198778Z\",\"expiry\":\"20260331\",\"right\":\"CALL\",\"ask\":3.52,\"volume\":0,\"open_interest\":0,\"bid\":3.45,\"strike\":653.0,\"gamma\":0.006057946439851856,\"date\":\"2026-02-04\",\"last\":3.13},\"maxValues\":{\"right\":\"PUT\",\"ask\":47.53,\"last\":3.13,\"theta\":-0.04775096534917367,\"gamma\":0.0072340018021045316,\"vega\":0.582969895251038,\"strike\":653.0,\"bid\":46.01,\"open_interest\":0,\"yearmonth\":202602,\"delta\":0.16316565275754105,\"date\":\"2026-02-04\",\"timestamp\":\"2026-02-04T15:36:55.388958Z\",\"volume\":16,\"expiry\":\"20260331\",\"iv\":0.1735144268606305},\"nullCount\":{\"strike\":0,\"bid\":0,\"theta\":0,\"gamma\":0,\"ask\":0,\"delta\":0,\"open_interest\":0,\"date\":0,\"right\":0,\"last\":0,\"timestamp\":0,\"volume\":0,\"vega\":0,\"expiry\":0,\"iv\":0,\"yearmonth\":0}}","tags":null,"baseRowId":null,"defaultRowCommitVersion":null,"clusteringProvider":null}}
{"add":{"path":"strike_partition=570/symbol=QQQ/part-00000-aa5a7397-9d3b-4cd4-92a0-4ec84fc91390-c000.snappy.parquet","partitionValues":{"symbol":"QQQ","strike_partition":"570"},"size":5066,"modificationTime":1770237415659,"dataChange":true,"stats":"{\"numRecords\":4,\"minValues\":{\"bid\":9.83,\"expiry\":\"20260331\",\"volume\":0,\"vega\":0.770061023413767,\"date\":\"2026-02-04\",\"iv\":0.2531467886838662,\"timestamp\":\"2026-02-04T15:36:15.799923Z\",\"theta\":-0.22534719432990613,\"open_interest\":0,\"strike\":573.0,\"last\":11.2,\"right\":\"CALL\",\"yearmonth\":202602,\"ask\":9.92,\"gamma\":0.0051958157714864965,\"delta\":-0.2782259488896372},\"maxValues\":{\"ask\":47.25,\"yearmonth\":202602,\"right\":\"PUT\",\"theta\":-0.1649810724627354,\"open_interest\":0,\"timestamp\":\"2026-02-04T15:36:19.661502Z\",\"last\":11.94,\"gamma\":0.0056040457556711405,\"strike\":578.0,\"date\":\"2026-02-04\",\"expiry\":\"20260331\",\"iv\":0.26214541723320267,\"bid\":45.85,\"vega\":0.7850590152696544,\"volume\":22,\"delta\":0.7510785950468681},\"nullCount\":{\"strike\":0,\"right\":0,\"volume\":0,\"gamma\":0,\"date\":0,\"yearmonth\":0,\"vega\":0,\"last\":0,\"theta\":0,\"bid\":0,\"open_interest\":0,\"timestamp\":0,\"iv\":0,\"expiry\":0,\"ask\":0,\"delta\":0}}","tags":null,"baseRowId":null,"defaultRowCommitVersion":null,"clusteringProvider":null}}
{"add":{"path":"strike_partition=580/symbol=QQQ/part-00000-536a8520-2b5e-47f3-96a0-0e0e9d7cf21d-c000.snappy.parquet","partitionValues":{"strike_partition":"580","symbol":"QQQ"},"size":5068,"modificationTime":1770237415659,"dataChange":true,"stats":"{\"numRecords\":4,\"minValues\":{\"last\":13.9,\"yearmonth\":202602,\"ask\":12.12,\"bid\":12.01,\"right\":\"CALL\",\"expiry\":\"20260331\",\"open_interest\":0,\"iv\":0.2403741944525254,\"strike\":583.0,\"theta\":-0.22906077911398626,\"date\":\"2026-02-04\",\"vega\":0.8280316026121142,\"timestamp\":\"2026-02-04T15:36:20.855878Z\",\"volume\":0,\"delta\":-0.3335644415723347,\"gamma\":0.005977656463601347},\"maxValues\":{\"vega\":0.8640253571993988,\"volume\":13,\"iv\":0.24942735457304768,\"right\":\"PUT\",\"last\":14.82,\"theta\":-0.16229589102854192,\"expiry\":\"20260331\",\"strike\":588.0,\"delta\":0.7007292927727228,\"ask\":39.49,\"open_interest\":0,\"timestamp\":\"2026-02-04T15:36:24.427597Z\",\"gamma\":0.0063828772971727295,\"yearmonth\":202602,\"bid\":38.16,\"date\":\"2026-02-04\"},\"nullCount\":{\"yearmonth\":0,\"vega\":0,\"open_interest\":0,\"theta\":0,\"volume\":0,\"iv\":0,\"delta\":0,\"gamma\":0,\"last\":0,\"ask\":0,\"bid\":0,\"timestamp\":0,\"right\":0,\"strike\":0,\"expiry\":0,\"date\":0}}","tags":null,"baseRowId":null,"defaultRowCommitVersion":null,"clusteringProvider":null}}
{"add":{"path":"strike_partition=590/symbol=QQQ/part-00000-796556e2-551d-4449-bd54-750e78aff34b-c000.snappy.parquet","partitionValues":{"strike_partition":"590","symbol":"QQQ"},"size":5090,"modificationTime":1770237415659,"dataChange":true,"stats":"{\"numRecords\":4,\"minValues\":{\"strike\":593.0,\"last\":16.82,\"expiry\":\"20260331\",\"iv\":0.23182588877207852,\"yearmonth\":202602,\"volume\":0,\"right\":\"CALL\",\"ask\":14.76,\"delta\":-0.39796188590441706,\"gamma\":0.006737943735386304,\"theta\":-0.2282998211151046,\"open_interest\":0,\"timestamp\":\"2026-02-04T15:36:25.621588Z\",\"bid\":14.65,\"vega\":0.869285416851767,\"date\":\"2026-02-04\"},\"maxValues\":{\"yearmonth\":202602,\"volume\":13,\"strike\":598.0,\"delta\":0.6409131426137046,\"date\":\"2026-02-04\",\"right\":\"PUT\",\"open_interest\":0,\"timestamp\":\"2026-02-04T15:36:29.200272Z\",\"gamma\":0.007151550432080866,\"bid\":31.37,\"theta\":-0.16590852576699078,\"ask\":32.12,\"last\":31.31,\"expiry\":\"20260331\",\"vega\":0.9155655710539428,\"iv\":0.23675500584277703},\"nullCount\":{\"timestamp\":0,\"volume\":0,\"open_interest\":0,\"delta\":0,\"yearmonth\":0,\"right\":0,\"last\":0,\"strike\":0,\"ask\":0,\"iv\":0,\"theta\":0,\"vega\":0,\"date\":0,\"bid\":0,\"expiry\":0,\"gamma\":0}}","tags":null,"baseRowId":null,"defaultRowCommitVersion":null,"clusteringProvider":null}}
{"add":{"path":"strike_partition=630/symbol=QQQ/part-00000-117d69bb-4b34-4262-8e4e-82c7f1718976-c000.snappy.parquet","partitionValues":{"symbol":"QQQ","strike_partition":"630"},"size":5074,"modificationTime":1770237415659,"dataChange":true,"stats":"{\"numRecords\":4,\"minValues\":{\"right\":\"CALL\",\"yearmonth\":202602,\"gamma\":0.007707984596901429,\"open_interest\":0,\"strike\":633.0,\"theta\":-0.17477592424072697,\"timestamp\":\"2026-02-04T15:36:44.652394Z\",\"delta\":-0.7368053497296873,\"bid\":7.35,\"expiry\":\"20260331\",\"iv\":0.18335777802993594,\"ask\":7.45,\"last\":6.7,\"volume\":0,\"vega\":0.7680488653806563,\"date\":\"2026-02-04\"},\"maxValues\":{\"volume\":15,\"strike\":638.0,\"last\":36.35,\"open_interest\":0,\"iv\":0.19229962377170254,\"right\":\"PUT\",\"ask\":36.12,\"theta\":-0.0938411244128119,\"yearmonth\":202602,\"delta\":0.32468804171920823,\"vega\":0.8818094863499937,\"timestamp\":\"2026-02-04T15:36:48.224942Z\",\"gamma\":0.008419039716714259,\"expiry\":\"20260331\",\"bid\":34.62,\"date\":\"2026-02-04\"},\"nullCount\":{\"date\":0,\"open_interest\":0,\"last\":0,\"iv\":0,\"expiry\":0,\"delta\":0,\"strike\":0,\"bid\":0,\"vega\":0,\"right\":0,\"gamma\":0,\"volume\":0,\"theta\":0,\"yearmonth\":0,\"ask\":0,\"timestamp\":0}}","tags":null,"baseRowId":null,"defaultRowCommitVersion":null,"clusteringProvider":null}}
{"add":{"path":"strike_partition=620/symbol=QQQ/part-00000-4ddce9a3-a7db-4a0e-bb16-a0808fdf041d-c000.snappy.parquet","partitionValues":{"strike_partition":"620","symbol":"QQQ"},"size":5089,"modificationTime":1770237415659,"dataChange":true,"stats":"{\"numRecords\":4,\"minValues\":{\"right\":\"CALL\",\"open_interest\":0,\"last\":11.3,\"strike\":623.0,\"iv\":0.19714708016947374,\"yearmonth\":202602,\"expiry\":\"20260331\",\"timestamp\":\"2026-02-04T15:36:39.901080Z\",\"theta\":-0.19741269714629794,\"vega\":0.8605076816694357,\"ask\":11.32,\"volume\":12,\"date\":\"2026-02-04\",\"gamma\":0.00817778933097079,\"delta\":-0.6428808066958173,\"bid\":11.2},\"maxValues\":{\"bid\":28.51,\"delta\":0.41148848029333895,\"date\":\"2026-02-04\",\"timestamp\":\"2026-02-04T15:36:43.466987Z\",\"open_interest\":0,\"volume\":63,\"ask\":29.84,\"yearmonth\":202602,\"vega\":0.9292630997648228,\"right\":\"PUT\",\"last\":29.0,\"expiry\":\"20260331\",\"gamma\":0.008456557596591849,\"strike\":628.0,\"iv\":0.20280875524214964,\"theta\":-0.11884830896830323},\"nullCount\":{\"gamma\":0,\"bid\":0,\"timestamp\":0,\"iv\":0,\"date\":0,\"strike\":0,\"volume\":0,\"right\":0,\"delta\":0,\"theta\":0,\"yearmonth\":0,\"vega\":0,\"expiry\":0,\"last\":0,\"ask\":0,\"open_interest\":0}}","tags":null,"baseRowId":null,"defaultRowCommitVersion":null,"clusteringProvider":null}}
{"add":{"path":"strike_partition=640/symbol=QQQ/part-00000-52b5eb46-5ccc-4923-bf39-bc3e6b63f983-c000.snappy.parquet","partitionValues":{"strike_partition":"640","symbol":"QQQ"},"size":5075,"modificationTime":1770237415660,"dataChange":true,"stats":"{\"numRecords\":4,\"minValues\":{\"right\":\"CALL\",\"last\":4.44,\"volume\":0,\"strike\":643.0,\"gamma\":0.006721631742749116,\"theta\":-0.1294840150591714,\"iv\":0.17510369122005978,\"vega\":0.6313518888107126,\"yearmonth\":202602,\"date\":\"2026-02-04\",\"ask\":4.59,\"timestamp\":\"2026-02-04T15:36:49.416957Z\",\"expiry\":\"20260331\",\"open_interest\":0,\"delta\":-0.8260573541136421,\"bid\":4.51},\"maxValues\":{\"volume\":129,\"delta\":0.23758516880231728,\"theta\":-0.06744939339643707,\"vega\":0.7071074117427667,\"yearmonth\":202602,\"right\":\"PUT\",\"timestamp\":\"2026-02-04T15:36:53.008140Z\",\"expiry\":\"20260331\",\"strike\":648.0,\"date\":\"2026-02-04\",\"bid\":41.94,\"open_interest\":0,\"gamma\":0.007986932983769502,\"last\":5.79,\"ask\":43.57,\"iv\":0.18163905981678358},\"nullCount\":{\"gamma\":0,\"expiry\":0,\"bid\":0,\"delta\":0,\"last\":0,\"ask\":0,\"volume\":0,\"iv\":0,\"open_interest\":0,\"timestamp\":0,\"right\":0,\"vega\":0,\"date\":0,\"yearmonth\":0,\"theta\":0,\"strike\":0}}","tags":null,"baseRowId":null,"defaultRowCommitVersion":null,"clusteringProvider":null}}
{"add":{"path":"strike_partition=610/symbol=QQQ/part-00000-42858e0b-7d2c-4b6a-8d30-063480d2e187-c000.snappy.parquet","partitionValues":{"strike_partition":"610","symbol":"QQQ"},"size":5081,"modificationTime":1770237415660,"dataChange":true,"stats":"{\"numRecords\":4,\"minValues\":{\"gamma\":0.007970482055730208,\"strike\":613.0,\"bid\":16.01,\"last\":14.75,\"theta\":-0.2144780430304607,\"vega\":0.9151083125758142,\"yearmonth\":202602,\"open_interest\":0,\"date\":\"2026-02-04\",\"iv\":0.20823961356350007,\"expiry\":\"20260331\",\"timestamp\":\"2026-02-04T15:36:35.144583Z\",\"volume\":7,\"right\":\"CALL\",\"ask\":16.13,\"delta\":-0.5539919490890833},\"maxValues\":{\"delta\":0.49343016610148893,\"vega\":0.9438263789753201,\"right\":\"PUT\",\"ask\":24.32,\"open_interest\":0,\"date\":\"2026-02-04\",\"gamma\":0.008290031677811763,\"timestamp\":\"2026-02-04T15:36:38.709520Z\",\"strike\":618.0,\"bid\":23.98,\"volume\":50,\"yearmonth\":202602,\"last\":24.2,\"iv\":0.21441334048734656,\"expiry\":\"20260331\",\"theta\":-0.14110109853106678},\"nullCount\":{\"yearmonth\":0,\"open_interest\":0,\"delta\":0,\"ask\":0,\"gamma\":0,\"strike\":0,\"bid\":0,\"iv\":0,\"vega\":0,\"expiry\":0,\"volume\":0,\"timestamp\":0,\"last\":0,\"date\":0,\"theta\":0,\"right\":0}}","tags":null,"baseRowId":null,"defaultRowCommitVersion":null,"clusteringProvider":null}}
{"commitInfo":{"timestamp":1770237415660,"operation":"WRITE","operationParameters":{"partitionBy":"[\"strike_partition\",\"symbol\"]","mode":"Append"},"engineInfo":"delta-rs:py-1.3.2","clientVersion":"delta-rs.py-1.3.2","operationMetrics":{"execution_time_ms":7,"num_added_files":10,"num_added_rows":38,"num_partitions":0,"num_removed_files":0}}}