{"add":{"path":"strike_partition=700/symbol=SPY/part-00000-45d6ffe6-074e-4a69-b51a-56a9af3caad1-c000.snappy.parquet","partitionValues":{"strike_partition":"700","symbol":"SPY"},"size":5054,"modificationTime":1770235506890,"dataChange":true,"stats":"{\"numRecords\":4,\"minValues\":{\"vega\":0.9808106524528135,\"delta\":-0.6838920835317159,\"expiry\":\"20260331\",\"theta\":-0.15093368873913704,\"ask\":7.47,\"volume\":0,\"yearmonth\":202602,\"gamma\":0.010509584464993532,\"right\":\"CALL\",\"bid\":7.41,\"last\":6.74,\"iv\":0.131595669230273,\"timestamp\":\"2026-02-04T15:04:46.186882Z\",\"date\":\"2026-02-04\",\"strike\":702.0,\"open_interest\":0},\"maxValues\":{\"ask\":24.55,\"volume\":61,\"iv\":0.1373003329313975,\"vega\":1.0098205140093688,\"strike\":707.0,\"right\":\"PUT\",\"theta\":-0.07387685311929104,\"gamma\":0.010767410748927304,\"date\":\"2026-02-04\",\"delta\":0.3894539161947616,\"bid\":24.13,\"last\":8.78,\"yearmonth\":202602,\"expiry\":\"20260331\",\"timestamp\":\"2026-02-04T15:04:49.751720Z\",\"open_interest\":0},\"nullCount\":{\"delta\":0,\"ask\":0,\"right\":0,\"bid\":0,\"open_interest\":0,\"timestamp\":0,\"last\":0,\"strike\":0,\"theta\":0,\"date\":0,\"volume\":0,\"gamma\":0,\"vega\":0,\"expiry\":0,\"yearmonth\":0,\"iv\":0}}","tags":null,"baseRowId":null,"defaultRowCommitVersion":null,"clusteringProvider":null}}
{"add":{"path":"strike_partition=720/symbol=SPY/part-00000-4c2bee49-9321-4bde-bada-143a8cdf37d7-c000.snappy.parquet","partitionValues":{"symbol":"SPY","strike_partition":"720"},"size":5069,"modificationTime":1770235506890,"dataChange":true,"stats":"{\"numRecords\":4,\"minValues\":{\"expiry\":\"20260331\",\"bid\":1.97,\"yearmonth\":202602,\"gamma\":0.006907003680702154,\"strike\":722.0,\"theta\":-0.08681228742240599,\"timestamp\":\"2026-02-04T15:04:55.728713Z\",\"iv\":0.11619727006163107,\"last\":1.8,\"right\":\"CALL\",\"delta\":-0.9194489769758308,\"volume\":1,\"date\":\"2026-02-04\",\"ask\":2.01,\"open_interest\":0,\"vega\":0.4224562808428445},\"maxValues\":{\"iv\":0.11893075847832521,\"gamma\":0.01006449373243175,\"expiry\":\"20260331\",\"timestamp\":\"2026-02-04T15:04:59.289175Z\",\"open_interest\":0,\"volume\":967,\"delta\":0.17429496461478752,\"theta\":-0.01422582930678118,\"vega\":0.6764096503509895,\"last\":37.1,\"bid\":37.87,\"strike\":727.0,\"right\":\"PUT\",\"yearmonth\":202602,\"ask\":40.89,\"date\":\"2026-02-04\"},\"nullCount\":{\"iv\":0,\"yearmonth\":0,\"open_interest\":0,\"bid\":0,\"ask\":0,\"delta\":0,\"gamma\":0,\"vega\":0,\"strike\":0,\"theta\":0,\"expiry\":0,\"date\":0,\"timestamp\":0,\"right\":0,\"last\":0,\"volume\":0}}","tags":null,"baseRowId":null,"defaultRowCommitVersion":null,"clusteringProvider":null}}
{"add":{"path":"strike_partition=730/symbol=SPY/part-00000-431c6fb6-358c-4471-a764-2a3f589f9b57-c000.snappy.parquet","partitionValues":{"symbol":"SPY","strike_partition":"730"},"size":5053,"modificationTime":1770235506891,"dataChange":true,"stats":"{\"numRecords\":4,\"minValues\":{\"last\":0.97,\"volume\":0,\"iv\":0.11306060409789717,\"open_interest\":0,\"timestamp\":\"2026-02-04T15:05:00.476863Z\",\"gamma\":0.0012433524801805896,\"date\":\"2026-02-04\",\"right\":\"CALL\",\"delta\":-1.0000000000000027,\"bid\":0.92,\"expiry\":\"20260331\",\"yearmonth\":202602,\"vega\":0.02054803340652711,\"ask\":0.94,\"theta\":-0.05212666279168854,\"strike\":732.0},\"maxValues\":{\"gamma\":0.008184810399648119,\"expiry\":\"20260331\",\"date\":\"2026-02-04\",\"last\":1.22,\"ask\":51.0,\"theta\":-2.2666313270747196e-12,\"timestamp\":\"2026-02-04T15:05:04.090808Z\",\"strike\":737.0,\"delta\":0.09819729125738107,\"yearmonth\":202602,\"vega\":0.5040612922497163,\"bid\":47.56,\"volume\":18,\"open_interest\":0,\"right\":\"PUT\",\"iv\":0.1142396247879902},\"nullCount\":{\"right\":0,\"delta\":0,\"iv\":0,\"vega\":0,\"date\":0,\"ask\":0,\"yearmonth\":0,\"gamma\":0,\"bid\":0,\"volume\":0,\"last\":0,\"timestamp\":0,\"strike\":0,\"expiry\":0,\"theta\":0,\"open_interest\":0}}","tags":null,"baseRowId":null,"defaultRowCommitVersion":null,"clusteringProvider":null}}
{"add":{"path":"strike_partition=650/symbol=SPY/part-00000-dfc33b5a-73f0-46be-9774-6ae33c553a66-c000.snappy.parquet","partitionValues":{"strike_partition":"650","symbol":"SPY"},"size":5065,"modificationTime":1770235506891,"dataChange":true,"stats":"{\"numRecords\":4,\"minValues\":{\"bid\":7.07,\"theta\":-0.1992109670298845,\"timestamp\":\"2026-02-04T15:04:21.019800Z\",\"iv\":0.19504951750855812,\"date\":\"2026-02-04\",\"ask\":7.11,\"vega\":0.7601799959169995,\"strike\":652.0,\"last\":8.45,\"expiry\":\"20260331\",\"volume\":0,\"right\":\"CALL\",\"open_interest\":0,\"gamma\":0.00556050999605529,\"delta\":-0.24690105263894646,\"yearmonth\":202602},\"maxValues\":{\"date\":\"2026-02-04\",\"bid\":45.37,\"ask\":45.81,\"gamma\":0.006127882913906927,\"strike\":657.0,\"vega\":0.8761571746277701,\"delta\":0.7858518307934095,\"volume\":204,\"right\":\"PUT\",\"theta\":-0.12542095433618972,\"iv\":0.20109301152840875,\"last\":41.5,\"yearmonth\":202602,\"expiry\":\"20260331\",\"timestamp\":\"2026-02-04T15:04:25.161412Z\",\"open_interest\":0},\"nullCount\":{\"ask\":0,\"right\":0,\"delta\":0,\"volume\":0,\"last\":0,\"gamma\":0,\"bid\":0,\"iv\":0,\"date\":0,\"timestamp\":0,\"strike\":0,\"open_interest\":0,\"yearmonth\":0,\"expiry\":0,\"theta\":0,\"vega\":0}}","tags":null,"baseRowId":null,"defaultRowCommitVersion":null,"clusteringProvider":null}}
{"add":{"path":"strike_partition=740/symbol=SPY/part-00000-27034832-69af-4359-824e-2622f22de8f3-c000.snappy.parquet","partitionValues":{"strike_partition":"740","symbol":"SPY"},"size":4801,"modificationTime":1770235506890,"dataChange":true,"stats":"{\"numRecords\":2,\"minValues\":{\"open_interest\":0,\"theta\":-0.03526220684544612,\"date\":\"2026-02-04\",\"yearmonth\":202602,\"timestamp\":\"2026-02-04T15:05:05.275598Z\",\"iv\":0.1126134667553646,\"expiry\":\"20260331\",\"gamma\":-3.9352066561061627e-16,\"vega\":-1.1368683772161603e-12,\"volume\":0,\"delta\":-0.9999999999999982,\"strike\":742.0,\"right\":\"CALL\",\"ask\":0.65,\"bid\":0.63},\"maxValues\":{\"volume\":2,\"date\":\"2026-02-04\",\"iv\":0.1126134667553646,\"ask\":55.94,\"delta\":0.05117239421120354,\"open_interest\":0,\"theta\":-3.339550858072471e-13,\"vega\":0.3236258293334968,\"strike\":742.0,\"gamma\":0.0035235639135673623,\"expiry\":\"20260331\",\"timestamp\":\"2026-02-04T15:05:06.475480Z\",\"right\":\"PUT\",\"bid\":52.43,\"yearmonth\":202602},\"nullCount\":{\"strike\":0,\"theta\":0,\"expiry\":0,\"right\":0,\"delta\":0,\"last\":0,\"gamma\":0,\"iv\":0,\"date\":0,\"open_interest\":0,\"vega\":0,\"volume\":0,\"timestamp\":0,\"yearmonth\":0,\"ask\":0,\"bid\":0}}","tags":null,"baseRowId":null,"defaultRowCommitVersion":null,"clusteringProvider":null}}
{"add":{"path":"strike_partition=660/symbol=SPY/part-00000-6c6729a5-05b4-421f-a285-4974934fa843-c000.snappy.parquet","partitionValues":{"symbol":"SPY","strike_partition":"660"},"size":5064,"modificationTime":1770235506890,"dataChange":true,"stats":"{\"numRecords\":4,\"minValues\":{\"theta\":-0.19635359067861202,\"expiry\":\"20260331\",\"date\":\"2026-02-04\",\"right\":\"CALL\",\"iv\":0.18256964633408004,\"volume\":0,\"gamma\":0.006646689725395821,\"last\":9.86,\"delta\":-0.3045378157281937,\"bid\":8.73,\"vega\":0.8669167132783215,\"yearmonth\":202602,\"ask\":8.78,\"timestamp\":\"2026-02-04T15:04:26.475156Z\",\"open_interest\":0,\"strike\":662.0},\"maxValues\":{\"theta\":-0.13239105383439842,\"expiry\":\"20260331\",\"vega\":0.9666139076714106,\"right\":\"PUT\",\"strike\":667.0,\"gamma\":0.007290243198415057,\"bid\":37.04,\"yearmonth\":202602,\"last\":32.6,\"timestamp\":\"2026-02-04T15:04:30.687796Z\",\"delta\":0.7348994601944432,\"open_interest\":0,\"iv\":0.1886284200505829,\"date\":\"2026-02-04\",\"ask\":37.3,\"volume\":172},\"nullCount\":{\"delta\":0,\"right\":0,\"yearmonth\":0,\"gamma\":0,\"volume\":0,\"vega\":0,\"timestamp\":0,\"bid\":0,\"last\":0,\"strike\":0,\"iv\":0,\"ask\":0,\"date\":0,\"theta\":0,\"open_interest\":0,\"expiry\":0}}","tags":null,"baseRowId":null,"defaultRowCommitVersion":null,"clusteringProvider":null}}
{"add":{"path":"strike_partition=710/symbol=SPY/part-00000-6a830f59-95a9-4d03-83b8-0afe9e651759-c000.snappy.parquet","partitionValues":{"strike_partition":"710","symbol":"SPY"},"size":5059,"modificationTime":1770235506891,"dataChange":true,"stats":"{\"numRecords\":4,\"minValues\":{\"vega\":-0.0,\"right\":\"CALL\",\"last\":3.61,\"ask\":4.05,\"volume\":0,\"yearmonth\":202602,\"theta\":-0.10626368552788845,\"gamma\":-0.0,\"date\":\"2026-02-04\",\"iv\":-0.0,\"delta\":-0.8039951519824142,\"expiry\":\"20260331\",\"timestamp\":\"2026-02-04T15:04:50.959753Z\",\"bid\":4.01,\"strike\":712.0,\"open_interest\":0},\"maxValues\":{\"delta\":0.22210042168338762,\"bid\":30.91,\"right\":\"PUT\",\"strike\":717.0,\"expiry\":\"20260331\",\"last\":30.44,\"ask\":31.38,\"vega\":0.8808507820534821,\"volume\":271,\"iv\":0.12661864430224437,\"yearmonth\":202602,\"open_interest\":0,\"timestamp\":\"2026-02-04T15:04:54.515320Z\",\"theta\":0.0,\"date\":\"2026-02-04\",\"gamma\":0.010587313643855666},\"nullCount\":{\"date\":0,\"bid\":0,\"volume\":0,\"right\":0,\"gamma\":0,\"iv\":0,\"expiry\":0,\"vega\":0,\"open_interest\":0,\"theta\":0,\"last\":0,\"delta\":0,\"ask\":0,\"yearmonth\":0,\"timestamp\":0,\"strike\":0}}","tags":null,"baseRowId":null,"defaultRowCommitVersion":null,"clusteringProvider":null}}
{"add":{"path":"strike_partition=640/symbol=SPY/part-00000-844cb32e-d300-4dec-9c0b-659f5bda9b9a-c000.snappy.parquet","partitionValues":{"strike_partition":"640","symbol":"SPY"},"size":5049,"modificationTime":1770235506890,"dataChange":true,"stats":"{\"numRecords\":4,\"minValues\":{\"timestamp\":\"2026-02-04T15:04:16.191411Z\",\"theta\":-0.1878834816019932,\"iv\":0.2070167028013127,\"expiry\":\"20260331\",\"last\":6.15,\"yearmonth\":202602,\"right\":\"CALL\",\"strike\":642.0,\"vega\":0.735407793359613,\"open_interest\":0,\"gamma\":0.004617912687367758,\"ask\":5.78,\"volume\":0,\"date\":\"2026-02-04\",\"bid\":5.74,\"delta\":-0.20088016318708166},\"maxValues\":{\"timestamp\":\"2026-02-04T15:04:19.801206Z\",\"ask\":54.56,\"vega\":0.764798186980487,\"iv\":0.2134719525332792,\"open_interest\":0,\"yearmonth\":202602,\"theta\":-0.115731571954246,\"last\":6.72,\"date\":\"2026-02-04\",\"gamma\":0.005118043551615328,\"delta\":0.8271770156447729,\"expiry\":\"20260331\",\"volume\":62,\"right\":\"PUT\",\"bid\":54.04,\"strike\":647.0},\"nullCount\":{\"ask\":0,\"strike\":0,\"open_interest\":0,\"date\":0,\"delta\":0,\"last\":0,\"theta\":0,\"volume\":0,\"expiry\":0,\"vega\":0,\"gamma\":0,\"timestamp\":0,\"right\":0,\"iv\":0,\"yearmonth\":0,\"bid\":0}}","tags":null,"baseRowId":null,"defaultRowCommitVersion":null,"clusteringProvider":null}}
{"add":{"path":"strike_partition=680/symbol=SPY/part-00000-ecfc34ee-163e-4440-8f66-18faf27aa4db-c000.snappy.parquet","partitionValues":{"symbol":"SPY","strike_partition":"680"},"size":5069,"modificationTime":1770235506891,"dataChange":true,"stats":"{\"numRecords\":4,\"minValues\":{\"delta\":-0.46293500057058173,\"last\":13.83,\"iv\":0.15623707409840465,\"theta\":-0.1919517263742314,\"date\":\"2026-02-04\",\"volume\":29,\"ask\":13.61,\"open_interest\":0,\"bid\":13.55,\"strike\":682.0,\"yearmonth\":202602,\"right\":\"CALL\",\"vega\":1.0319960169301439,\"timestamp\":\"2026-02-04T15:04:36.677393Z\",\"expiry\":\"20260331\",\"gamma\":0.009071924303520641},\"maxValues\":{\"right\":\"PUT\",\"expiry\":\"20260331\",\"vega\":1.0539267067342877,\"yearmonth\":202602,\"date\":\"2026-02-04\",\"ask\":21.9,\"last\":19.6,\"timestamp\":\"2026-02-04T15:04:40.243445Z\",\"delta\":0.5945448211302041,\"iv\":0.16283208124168413,\"theta\":-0.11818582086843676,\"strike\":687.0,\"volume\":240,\"open_interest\":0,\"gamma\":0.00970934049014324,\"bid\":21.69},\"nullCount\":{\"gamma\":0,\"timestamp\":0,\"right\":0,\"open_interest\":0,\"vega\":0,\"yearmonth\":0,\"last\":0,\"delta\":0,\"bid\":0,\"theta\":0,\"strike\":0,\"ask\":0,\"iv\":0,\"date\":0,\"volume\":0,\"expiry\":0}}","tags":null,"baseRowId":null,"defaultRowCommitVersion":null,"clusteringProvider":null}}
{"add":{"path":"strike_partition=630/symbol=SPY/part-00000-537d4792-f100-4709-ae5f-af0e6536f89f-c000.snappy.parquet","partitionValues":{"strike_partition":"630","symbol":"SPY"},"size":5046,"modificationTime":1770235506891,"dataChange":true,"stats":"{\"numRecords\":4,\"minValues\":{\"expiry\":\"20260331\",\"gamma\":0.003810964189153418,\"last\":5.86,\"bid\":4.65,\"iv\":0.21941181841346588,\"vega\":0.6102097356602201,\"volume\":0,\"timestamp\":\"2026-02-04T15:04:11.374309Z\",\"right\":\"CALL\",\"strike\":632.0,\"open_interest\":0,\"date\":\"2026-02-04\",\"yearmonth\":202602,\"theta\":-0.1743834383606213,\"delta\":-0.1633292225636107,\"ask\":4.69},\"maxValues\":{\"yearmonth\":202602,\"expiry\":\"20260331\",\"timestamp\":\"2026-02-04T15:04:14.934921Z\",\"date\":\"2026-02-04\",\"delta\":0.8596564592469073,\"bid\":63.06,\"iv\":0.22521427893917126,\"last\":6.39,\"vega\":0.6435076030042817,\"ask\":63.52,\"theta\":-0.11638537567143281,\"right\":\"PUT\",\"strike\":637.0,\"volume\":129,\"open_interest\":0,\"gamma\":0.004250014016635611},\"nullCount\":{\"iv\":0,\"expiry\":0,\"bid\":0,\"volume\":0,\"right\":0,\"timestamp\":0,\"last\":0,\"date\":0,\"open_interest\":0,\"delta\":0,\"strike\":0,\"gamma\":0,\"ask\":0,\"yearmonth\":0,\"vega\":0,\"theta\":0}}","tags":null,"baseRowId":null,"defaultRowCommitVersion":null,"clusteringProvider":null}}
{"add":{"path":"strike_partition=690/symbol=SPY/part-00000-6a4badbc-96bc-48db-89c3-9f820743bd56-c000.snappy.parquet","partitionValues":{"strike_partition":"690","symbol":"SPY"},"size":5070,"modificationTime":1770235506891,"dataChange":true,"stats":"{\"numRecords\":4,\"minValues\":{\"volume\":23,\"ask\":12.32,\"date\":\"2026-02-04\",\"open_interest\":0,\"theta\":-0.17877875290301226,\"delta\":-0.5667497419522738,\"timestamp\":\"2026-02-04T15:04:41.430255Z\",\"iv\":0.143339021711242,\"vega\":1.0430864677417802,\"right\":\"CALL\",\"yearmonth\":202602,\"bid\":12.26,\"strike\":692.0,\"last\":12.2,\"expiry\":\"20260331\",\"gamma\":0.01018061823353771},\"maxValues\":{\"gamma\":0.010552364917680057,\"expiry\":\"20260331\",\"ask\":19.28,\"last\":23.08,\"date\":\"2026-02-04\",\"strike\":697.0,\"delta\":0.49913192843737414,\"bid\":19.04,\"volume\":146,\"yearmonth\":202602,\"timestamp\":\"2026-02-04T15:04:44.991991Z\",\"open_interest\":0,\"right\":\"PUT\",\"iv\":0.14970809386689232,\"theta\":-0.09795156019226425,\"vega\":1.0675558793338702},\"nullCount\":{\"delta\":0,\"gamma\":0,\"right\":0,\"open_interest\":0,\"ask\":0,\"bid\":0,\"theta\":0,\"strike\":0,\"volume\":0,\"iv\":0,\"yearmonth\":0,\"vega\":0,\"expiry\":0,\"timestamp\":0,\"date\":0,\"last\":0}}","tags":null,"baseRowId":null,"defaultRowCommitVersion":null,"clusteringProvider":null}}
{"add":{"path":"strike_partition=670/symbol=SPY/part-00000-8b7951df-7ae9-43a8-afe1-192d011f4d33-c000.snappy.parquet","partitionValues":{"strike_partition":"670","symbol":"SPY"},"size":5069,"modificationTime":1770235506891,"dataChange":true,"stats":"{\"numRecords\":4,\"minValues\":{\"bid\":10.88,\"delta\":-0.3757676859795649,\"vega\":0.9628199891206215,\"open_interest\":0,\"theta\":-0.1968254678107435,\"strike\":672.0,\"gamma\":0.007845556097661313,\"ask\":10.93,\"expiry\":\"20260331\",\"volume\":0,\"iv\":0.1695420763464943,\"yearmonth\":202602,\"right\":\"CALL\",\"last\":13.07,\"timestamp\":\"2026-02-04T15:04:31.925956Z\",\"date\":\"2026-02-04\"},\"maxValues\":{\"theta\":-0.12792781721418223,\"bid\":29.05,\"open_interest\":0,\"volume\":89,\"yearmonth\":202602,\"vega\":1.0192113242262906,\"ask\":29.32,\"delta\":0.6718872993689398,\"gamma\":0.008520193200300903,\"last\":29.24,\"expiry\":\"20260331\",\"timestamp\":\"2026-02-04T15:04:35.492508Z\",\"date\":\"2026-02-04\",\"strike\":677.0,\"right\":\"PUT\",\"iv\":0.1758695997496354},\"nullCount\":{\"theta\":0,\"ask\":0,\"delta\":0,\"last\":0,\"gamma\":0,\"expiry\":0,\"right\":0,\"bid\":0,\"open_interest\":0,\"vega\":0,\"timestamp\":0,\"strike\":0,\"date\":0,\"yearmonth\":0,\"volume\":0,\"iv\":0}}","tags":null,"baseRowId":null,"defaultRowCommitVersion":null,"clusteringProvider":null}}
{"commitInfo":{"timestamp":1770235506891,"operation":"WRITE","operationParameters":{"partitionBy":"[\"strike_partition\",\"symbol\"]","mode":"Append"},"engineInfo":"delta-rs:py-1.3.2","operationMetrics":{"execution_time_ms":13,"num_added_files":12,"num_added_rows":46,"num_partitions":0,"num_removed_files":0},"clientVersion":"delta-rs.py-1.3.2"}}