{"add":{"path":"strike_partition=590/symbol=QQQ/part-00000-4a141cad-b978-4884-8039-2347808635b6-c000.snappy.parquet","partitionValues":{"symbol":"QQQ","strike_partition":"590"},"size":4972,"modificationTime":1770307084868,"dataChange":true,"stats":"{\"numRecords\":4,\"minValues\":{\"ask\":19.76,\"strike\":592.0,\"right\":\"CALL\",\"bid\":19.04,\"last\":17.5,\"open_interest\":0,\"theta\":-0.2491989093228355,\"volume\":0,\"yearmonth\":202602,\"timestamp\":\"2026-02-05T10:57:48.708272Z\",\"delta\":-0.0,\"date\":\"2026-02-05\",\"iv\":-0.0,\"expiry\":\"20260327\",\"gamma\":-0.0,\"vega\":-0.0},\"maxValues\":{\"open_interest\":0,\"timestamp\":\"2026-02-05T10:57:52.358200Z\",\"bid\":24.08,\"delta\":0.5288470284578604,\"volume\":35,\"date\":\"2026-02-05\",\"last\":20.96,\"ask\":27.66,\"vega\":0.8752673648868523,\"gamma\":0.007305896383230725,\"yearmonth\":202602,\"strike\":597.0,\"right\":\"PUT\",\"theta\":0.0,\"expiry\":\"20260327\",\"iv\":0.2492444508367376},\"nullCount\":{\"volume\":0,\"vega\":0,\"last\":0,\"timestamp\":0,\"right\":0,\"delta\":0,\"date\":0,\"bid\":0,\"open_interest\":0,\"yearmonth\":0,\"theta\":0,\"gamma\":0,\"expiry\":0,\"strike\":0,\"iv\":0,\"ask\":0}}","tags":null,"baseRowId":null,"defaultRowCommitVersion":null,"clusteringProvider":null}}
{"add":{"path":"strike_partition=610/symbol=QQQ/part-00000-5493ff00-4590-4061-9986-eb700f237c8c-c000.snappy.parquet","partitionValues":{"strike_partition":"610","symbol":"QQQ"},"size":4756,"modificationTime":1770307084868,"dataChange":true,"stats":"{\"numRecords\":2,\"minValues\":{\"open_interest\":0,\"strike\":612.0,\"bid\":13.9,\"ask\":14.5,\"yearmonth\":202602,\"iv\":-0.0,\"delta\":-0.0,\"date\":\"2026-02-05\",\"expiry\":\"20260327\",\"gamma\":-0.0,\"theta\":-0.0,\"volume\":0,\"vega\":-0.0,\"right\":\"CALL\",\"timestamp\":\"2026-02-05T10:57:58.499621Z\"},\"maxValues\":{\"vega\":0.0,\"iv\":0.0,\"volume\":0,\"timestamp\":\"2026-02-05T10:57:59.728473Z\",\"bid\":26.01,\"gamma\":0.0,\"strike\":612.0,\"right\":\"PUT\",\"date\":\"2026-02-05\",\"open_interest\":0,\"ask\":29.66,\"delta\":0.0,\"theta\":0.0,\"expiry\":\"20260327\",\"yearmonth\":202602},\"nullCount\":{\"right\":0,\"delta\":0,\"ask\":0,\"vega\":0,\"bid\":0,\"timestamp\":0,\"date\":0,\"last\":0,\"yearmonth\":0,\"strike\":0,\"iv\":0,\"open_interest\":0,\"gamma\":0,\"theta\":0,\"expiry\":0,\"volume\":0}}","tags":null,"baseRowId":null,"defaultRowCommitVersion":null,"clusteringProvider":null}}
{"add":{"path":"strike_partition=600/symbol=QQQ/part-00000-f66fec81-a74f-44e8-b1b9-6032f0b2b35b-c000.snappy.parquet","partitionValues":{"strike_partition":"600","symbol":"QQQ"},"size":4962,"modificationTime":1770307084867,"dataChange":true,"stats":"{\"numRecords\":4,\"minValues\":{\"last\":23.3,\"ask\":17.03,\"expiry\":\"20260327\",\"delta\":-0.0,\"theta\":-0.22989354476009893,\"yearmonth\":202602,\"vega\":-0.0,\"right\":\"CALL\",\"timestamp\":\"2026-02-05T10:57:53.584432Z\",\"open_interest\":0,\"gamma\":-0.0,\"date\":\"2026-02-05\",\"strike\":602.0,\"bid\":16.42,\"iv\":-0.0,\"volume\":0},\"maxValues\":{\"vega\":0.8598818852767387,\"gamma\":0.0076847859657804135,\"date\":\"2026-02-05\",\"ask\":27.27,\"volume\":1,\"bid\":23.51,\"theta\":0.0,\"strike\":607.0,\"last\":23.3,\"delta\":0.45220396207405056,\"iv\":0.23590093719328598,\"yearmonth\":202602,\"timestamp\":\"2026-02-05T10:57:57.273017Z\",\"open_interest\":0,\"right\":\"PUT\",\"expiry\":\"20260327\"},\"nullCount\":{\"theta\":0,\"vega\":0,\"timestamp\":0,\"yearmonth\":0,\"strike\":0,\"expiry\":0,\"iv\":0,\"ask\":0,\"right\":0,\"gamma\":0,\"open_interest\":0,\"date\":0,\"volume\":0,\"delta\":0,\"last\":0,\"bid\":0}}","tags":null,"baseRowId":null,"defaultRowCommitVersion":null,"clusteringProvider":null}}
{"commitInfo":{"timestamp":1770307084868,"operation":"WRITE","operationParameters":{"mode":"Append","partitionBy":"[\"strike_partition\",\"symbol\"]"},"engineInfo":"delta-rs:py-1.3.2","operationMetrics":{"execution_time_ms":4,"num_added_files":3,"num_added_rows":10,"num_partitions":0,"num_removed_files":0},"clientVersion":"delta-rs.py-1.3.2"}}