{"add":{"path":"strike_partition=600/symbol=QQQ/part-00000-2aee5012-6d40-4634-bb9a-90c6fbe1de1d-c000.snappy.parquet","partitionValues":{"strike_partition":"600","symbol":"QQQ"},"size":5072,"modificationTime":1770316021669,"dataChange":true,"stats":"{\"numRecords\":4,\"minValues\":{\"theta\":-0.2414799017036664,\"delta\":-0.5190722149923799,\"gamma\":0.007599628822778851,\"vega\":0.8803388756458723,\"iv\":0.22943092347511346,\"ask\":19.07,\"timestamp\":\"2026-02-05T13:26:48.088308Z\",\"expiry\":\"20260327\",\"right\":\"CALL\",\"date\":\"2026-02-05\",\"last\":19.33,\"bid\":18.6,\"volume\":0,\"open_interest\":0,\"yearmonth\":202602,\"strike\":601.0},\"maxValues\":{\"vega\":0.8900607323606771,\"theta\":-0.1745808783499001,\"delta\":0.529462574144109,\"strike\":606.0,\"iv\":0.2381668082884795,\"ask\":22.91,\"last\":22.89,\"date\":\"2026-02-05\",\"yearmonth\":202602,\"gamma\":0.007953153239255543,\"timestamp\":\"2026-02-05T13:26:51.774339Z\",\"bid\":22.44,\"right\":\"PUT\",\"volume\":13,\"open_interest\":0,\"expiry\":\"20260327\"},\"nullCount\":{\"strike\":0,\"volume\":0,\"timestamp\":0,\"expiry\":0,\"bid\":0,\"last\":0,\"open_interest\":0,\"date\":0,\"right\":0,\"vega\":0,\"ask\":0,\"delta\":0,\"theta\":0,\"iv\":0,\"yearmonth\":0,\"gamma\":0}}","tags":null,"baseRowId":null,"defaultRowCommitVersion":null,"clusteringProvider":null}}
{"add":{"path":"strike_partition=610/symbol=QQQ/part-00000-50b10ddc-44f8-4196-a269-ce57f0c0ea1c-c000.snappy.parquet","partitionValues":{"strike_partition":"610","symbol":"QQQ"},"size":5071,"modificationTime":1770316021669,"dataChange":true,"stats":"{\"numRecords\":4,\"minValues\":{\"ask\":13.8,\"open_interest\":0,\"right\":\"CALL\",\"delta\":-0.6025511234810904,\"iv\":0.21728185286701204,\"theta\":-0.22223403159252264,\"vega\":0.8621097517011478,\"date\":\"2026-02-05\",\"volume\":0,\"strike\":611.0,\"expiry\":\"20260327\",\"timestamp\":\"2026-02-05T13:26:53.003372Z\",\"last\":13.21,\"gamma\":0.008002856149093268,\"yearmonth\":202602,\"bid\":13.36},\"maxValues\":{\"bid\":25.76,\"volume\":3,\"open_interest\":0,\"strike\":616.0,\"iv\":0.22488571493250042,\"delta\":0.44953831687108886,\"right\":\"PUT\",\"gamma\":0.008281125359070786,\"theta\":-0.15529342036023408,\"vega\":0.8749436730520479,\"expiry\":\"20260327\",\"yearmonth\":202602,\"ask\":29.22,\"timestamp\":\"2026-02-05T13:26:56.687349Z\",\"last\":15.5,\"date\":\"2026-02-05\"},\"nullCount\":{\"ask\":0,\"strike\":0,\"open_interest\":0,\"yearmonth\":0,\"delta\":0,\"vega\":0,\"bid\":0,\"right\":0,\"timestamp\":0,\"expiry\":0,\"gamma\":0,\"iv\":0,\"date\":0,\"volume\":0,\"last\":0,\"theta\":0}}","tags":null,"baseRowId":null,"defaultRowCommitVersion":null,"clusteringProvider":null}}
{"add":{"path":"strike_partition=590/symbol=QQQ/part-00000-305b0afe-b4b8-4613-8930-df5defbccb30-c000.snappy.parquet","partitionValues":{"symbol":"QQQ","strike_partition":"590"},"size":5083,"modificationTime":1770316021669,"dataChange":true,"stats":"{\"numRecords\":4,\"minValues\":{\"bid\":16.79,\"open_interest\":0,\"theta\":-0.251258931481793,\"date\":\"2026-02-05\",\"gamma\":0.007023212014535254,\"delta\":-0.4416972170044767,\"expiry\":\"20260327\",\"iv\":0.24457608948175313,\"yearmonth\":202602,\"ask\":17.26,\"right\":\"CALL\",\"last\":15.8,\"volume\":0,\"strike\":591.0,\"timestamp\":\"2026-02-05T13:26:43.175099Z\",\"vega\":0.8616172555432513},\"maxValues\":{\"last\":23.51,\"timestamp\":\"2026-02-05T13:26:46.861287Z\",\"expiry\":\"20260327\",\"iv\":0.250882432458327,\"gamma\":0.007400313264305517,\"ask\":29.88,\"vega\":0.8729411644411549,\"bid\":26.01,\"strike\":596.0,\"volume\":5,\"theta\":-0.18597513993635673,\"open_interest\":0,\"date\":\"2026-02-05\",\"yearmonth\":202602,\"delta\":0.5963965887492712,\"right\":\"PUT\"},\"nullCount\":{\"last\":0,\"strike\":0,\"volume\":0,\"bid\":0,\"right\":0,\"timestamp\":0,\"open_interest\":0,\"delta\":0,\"vega\":0,\"date\":0,\"iv\":0,\"gamma\":0,\"ask\":0,\"yearmonth\":0,\"expiry\":0,\"theta\":0}}","tags":null,"baseRowId":null,"defaultRowCommitVersion":null,"clusteringProvider":null}}
{"commitInfo":{"timestamp":1770316021669,"operation":"WRITE","operationParameters":{"partitionBy":"[\"strike_partition\",\"symbol\"]","mode":"Append"},"engineInfo":"delta-rs:py-1.3.2","operationMetrics":{"execution_time_ms":3,"num_added_files":3,"num_added_rows":12,"num_partitions":0,"num_removed_files":0},"clientVersion":"delta-rs.py-1.3.2"}}