{"add":{"path":"strike_partition=270/symbol=IWM/part-00000-dc074ef1-a38f-48fb-8f00-365de2720c07-c000.snappy.parquet","partitionValues":{"strike_partition":"270","symbol":"IWM"},"size":4899,"modificationTime":1770308642005,"dataChange":true,"stats":"{\"numRecords\":2,\"minValues\":{\"strike\":272.0,\"bid\":3.59,\"right\":\"CALL\",\"vega\":0.31975416308815596,\"date\":\"2026-02-05\",\"open_interest\":0,\"timestamp\":\"2026-02-05T11:23:59.537822Z\",\"gamma\":0.016355076702847773,\"ask\":3.67,\"volume\":0,\"theta\":-0.08148000419238555,\"last\":3.56,\"yearmonth\":202602,\"expiry\":\"20260327\",\"delta\":-0.7195459655062398,\"iv\":0.21853378523883296},\"maxValues\":{\"timestamp\":\"2026-02-05T11:24:00.764740Z\",\"last\":3.56,\"strike\":272.0,\"expiry\":\"20260327\",\"date\":\"2026-02-05\",\"ask\":16.94,\"delta\":0.2949186052028617,\"iv\":0.2210844196938539,\"gamma\":0.016699673365965704,\"right\":\"PUT\",\"volume\":2,\"open_interest\":0,\"theta\":-0.04671783556527487,\"vega\":0.32563685702531053,\"yearmonth\":202602,\"bid\":16.55},\"nullCount\":{\"iv\":0,\"right\":0,\"theta\":0,\"timestamp\":0,\"gamma\":0,\"expiry\":0,\"vega\":0,\"volume\":0,\"strike\":0,\"ask\":0,\"open_interest\":0,\"date\":0,\"yearmonth\":0,\"delta\":0,\"bid\":0,\"last\":0}}","tags":null,"baseRowId":null,"defaultRowCommitVersion":null,"clusteringProvider":null}}
{"add":{"path":"strike_partition=250/symbol=IWM/part-00000-9acdb756-8b58-48e9-8d50-61660feed599-c000.snappy.parquet","partitionValues":{"strike_partition":"250","symbol":"IWM"},"size":4801,"modificationTime":1770308642005,"dataChange":true,"stats":"{\"numRecords\":2,\"minValues\":{\"ask\":6.68,\"bid\":6.59,\"gamma\":0.01584388804901625,\"timestamp\":\"2026-02-05T11:23:48.073812Z\",\"strike\":252.0,\"open_interest\":0,\"vega\":0.35657505456892835,\"iv\":0.2535016341112855,\"delta\":-0.37518669022972034,\"theta\":-0.10977371586523255,\"date\":\"2026-02-05\",\"yearmonth\":202602,\"volume\":0,\"expiry\":\"20260327\",\"right\":\"CALL\"},\"maxValues\":{\"open_interest\":0,\"bid\":13.52,\"volume\":0,\"theta\":-0.07741022312008727,\"ask\":13.96,\"vega\":0.36483766720845967,\"expiry\":\"20260327\",\"gamma\":0.015927181400616622,\"yearmonth\":202602,\"iv\":0.2557512463097295,\"delta\":0.6468661166548717,\"date\":\"2026-02-05\",\"timestamp\":\"2026-02-05T11:23:49.706866Z\",\"strike\":252.0,\"right\":\"PUT\"},\"nullCount\":{\"last\":0,\"volume\":0,\"gamma\":0,\"date\":0,\"delta\":0,\"vega\":0,\"open_interest\":0,\"yearmonth\":0,\"theta\":0,\"bid\":0,\"ask\":0,\"timestamp\":0,\"expiry\":0,\"right\":0,\"strike\":0,\"iv\":0}}","tags":null,"baseRowId":null,"defaultRowCommitVersion":null,"clusteringProvider":null}}
{"add":{"path":"strike_partition=260/symbol=IWM/part-00000-998e050b-4e3f-4ecb-8a54-6d609c280a49-c000.snappy.parquet","partitionValues":{"strike_partition":"260","symbol":"IWM"},"size":4969,"modificationTime":1770308642005,"dataChange":true,"stats":"{\"numRecords\":4,\"minValues\":{\"vega\":0.35253574470784343,\"theta\":-0.10362934499248766,\"gamma\":0.01767535372589609,\"date\":\"2026-02-05\",\"yearmonth\":202602,\"open_interest\":0,\"volume\":0,\"bid\":5.35,\"ask\":5.44,\"right\":\"CALL\",\"timestamp\":\"2026-02-05T11:23:53.802153Z\",\"strike\":262.0,\"iv\":0.22479538014808834,\"delta\":-0.6363244063433504,\"expiry\":\"20260327\"},\"maxValues\":{\"theta\":-0.05740073228574616,\"volume\":10,\"right\":\"PUT\",\"open_interest\":0,\"gamma\":0.01838642325968237,\"yearmonth\":202602,\"delta\":0.47607772256080105,\"strike\":267.0,\"bid\":13.3,\"date\":\"2026-02-05\",\"timestamp\":\"2026-02-05T11:23:58.305372Z\",\"ask\":13.71,\"iv\":0.23690809504644522,\"expiry\":\"20260327\",\"vega\":0.37178881189251367},\"nullCount\":{\"last\":0,\"gamma\":0,\"yearmonth\":0,\"iv\":0,\"date\":0,\"right\":0,\"timestamp\":0,\"delta\":0,\"volume\":0,\"theta\":0,\"expiry\":0,\"ask\":0,\"bid\":0,\"open_interest\":0,\"vega\":0,\"strike\":0}}","tags":null,"baseRowId":null,"defaultRowCommitVersion":null,"clusteringProvider":null}}
{"add":{"path":"strike_partition=240/symbol=IWM/part-00000-39e23e43-eb33-40d2-8b1e-dc1c532532f1-c000.snappy.parquet","partitionValues":{"strike_partition":"240","symbol":"IWM"},"size":4899,"modificationTime":1770308641834,"dataChange":true,"stats":"{\"numRecords\":2,\"minValues\":{\"iv\":0.26509582264992926,\"expiry\":\"20260327\",\"vega\":0.3328895276429158,\"bid\":5.12,\"delta\":-0.30336335125299074,\"last\":4.77,\"gamma\":0.013900697576929045,\"theta\":-0.10975034024614772,\"date\":\"2026-02-05\",\"yearmonth\":202602,\"strike\":247.0,\"timestamp\":\"2026-02-05T11:23:45.674220Z\",\"right\":\"CALL\",\"open_interest\":0,\"ask\":5.19,\"volume\":0},\"maxValues\":{\"right\":\"PUT\",\"volume\":14,\"expiry\":\"20260327\",\"ask\":17.56,\"timestamp\":\"2026-02-05T11:23:46.874036Z\",\"open_interest\":0,\"gamma\":0.013953020180467195,\"last\":4.77,\"delta\":0.7183373549332818,\"strike\":247.0,\"date\":\"2026-02-05\",\"vega\":0.34495352741677276,\"yearmonth\":202602,\"theta\":-0.07938436072051758,\"iv\":0.26799839735435854,\"bid\":16.92},\"nullCount\":{\"strike\":0,\"expiry\":0,\"volume\":0,\"bid\":0,\"theta\":0,\"iv\":0,\"yearmonth\":0,\"vega\":0,\"ask\":0,\"last\":0,\"right\":0,\"gamma\":0,\"timestamp\":0,\"open_interest\":0,\"delta\":0,\"date\":0}}","tags":null,"baseRowId":null,"defaultRowCommitVersion":null,"clusteringProvider":null}}
{"commitInfo":{"timestamp":1770308642005,"operation":"WRITE","operationParameters":{"partitionBy":"[\"strike_partition\",\"symbol\"]","mode":"Append"},"engineInfo":"delta-rs:py-1.3.2","operationMetrics":{"execution_time_ms":173,"num_added_files":4,"num_added_rows":10,"num_partitions":0,"num_removed_files":0},"clientVersion":"delta-rs.py-1.3.2"}}