{"add":{"path":"strike_partition=620/symbol=QQQ/part-00000-fb669045-a161-447b-ad16-cd96cdaa3ead-c000.snappy.parquet","partitionValues":{"strike_partition":"620","symbol":"QQQ"},"size":4991,"modificationTime":1770235377480,"dataChange":true,"stats":"{\"numRecords\":4,\"minValues\":{\"gamma\":-0.0,\"vega\":-0.0,\"bid\":11.02,\"iv\":-0.0,\"right\":\"CALL\",\"ask\":11.13,\"open_interest\":0,\"strike\":623.0,\"date\":\"2026-02-04\",\"timestamp\":\"2026-02-04T15:02:41.716728Z\",\"volume\":12,\"expiry\":\"20260331\",\"theta\":-0.17792485908319122,\"last\":10.4,\"yearmonth\":202602,\"delta\":-0.0},\"maxValues\":{\"vega\":0.871425167155552,\"gamma\":0.008220313056261285,\"expiry\":\"20260331\",\"last\":29.0,\"open_interest\":0,\"strike\":628.0,\"timestamp\":\"2026-02-04T15:02:45.285625Z\",\"iv\":0.19544476062586186,\"theta\":0.0,\"date\":\"2026-02-04\",\"right\":\"PUT\",\"ask\":29.78,\"delta\":0.3649251518552081,\"bid\":28.31,\"volume\":56,\"yearmonth\":202602},\"nullCount\":{\"last\":0,\"delta\":0,\"vega\":0,\"date\":0,\"volume\":0,\"expiry\":0,\"theta\":0,\"open_interest\":0,\"yearmonth\":0,\"bid\":0,\"strike\":0,\"timestamp\":0,\"right\":0,\"ask\":0,\"iv\":0,\"gamma\":0}}","tags":null,"baseRowId":null,"defaultRowCommitVersion":null,"clusteringProvider":null}}
{"add":{"path":"strike_partition=590/symbol=QQQ/part-00000-118fbfff-cc4a-485e-8d62-149ab9dec2c1-c000.snappy.parquet","partitionValues":{"strike_partition":"590","symbol":"QQQ"},"size":4947,"modificationTime":1770235377480,"dataChange":true,"stats":"{\"numRecords\":4,\"minValues\":{\"theta\":-0.0,\"gamma\":-0.0,\"strike\":593.0,\"last\":16.82,\"volume\":0,\"yearmonth\":202602,\"open_interest\":0,\"date\":\"2026-02-04\",\"iv\":-0.0,\"vega\":-0.0,\"bid\":14.51,\"ask\":14.64,\"timestamp\":\"2026-02-04T15:02:27.169351Z\",\"right\":\"CALL\",\"delta\":-0.0,\"expiry\":\"20260331\"},\"maxValues\":{\"bid\":30.82,\"volume\":14,\"timestamp\":\"2026-02-04T15:02:30.980864Z\",\"open_interest\":0,\"theta\":0.0,\"ask\":32.08,\"date\":\"2026-02-04\",\"gamma\":0.0,\"expiry\":\"20260331\",\"last\":31.31,\"yearmonth\":202602,\"strike\":598.0,\"right\":\"PUT\",\"vega\":0.0,\"iv\":0.0,\"delta\":0.0},\"nullCount\":{\"iv\":0,\"last\":0,\"date\":0,\"yearmonth\":0,\"timestamp\":0,\"bid\":0,\"right\":0,\"theta\":0,\"open_interest\":0,\"expiry\":0,\"strike\":0,\"delta\":0,\"gamma\":0,\"ask\":0,\"volume\":0,\"vega\":0}}","tags":null,"baseRowId":null,"defaultRowCommitVersion":null,"clusteringProvider":null}}
{"add":{"path":"strike_partition=650/symbol=QQQ/part-00000-349516fc-e669-4775-8bf0-1c8392e076d3-c000.snappy.parquet","partitionValues":{"strike_partition":"650","symbol":"QQQ"},"size":4899,"modificationTime":1770235377480,"dataChange":true,"stats":"{\"numRecords\":2,\"minValues\":{\"ask\":3.44,\"timestamp\":\"2026-02-04T15:02:56.017577Z\",\"vega\":-0.0,\"theta\":-0.1022878877359128,\"last\":3.13,\"right\":\"CALL\",\"bid\":3.37,\"date\":\"2026-02-04\",\"open_interest\":0,\"delta\":-0.0,\"expiry\":\"20260331\",\"gamma\":-0.0,\"strike\":653.0,\"volume\":0,\"yearmonth\":202602,\"iv\":-0.0},\"maxValues\":{\"timestamp\":\"2026-02-04T15:02:57.207809Z\",\"bid\":45.99,\"gamma\":0.006064617200341193,\"volume\":11,\"delta\":0.16145729310427334,\"iv\":0.17199362437883686,\"expiry\":\"20260331\",\"ask\":47.7,\"vega\":0.5835859323748815,\"right\":\"PUT\",\"date\":\"2026-02-04\",\"yearmonth\":202602,\"open_interest\":0,\"theta\":0.0,\"strike\":653.0,\"last\":3.13},\"nullCount\":{\"timestamp\":0,\"bid\":0,\"volume\":0,\"last\":0,\"vega\":0,\"right\":0,\"gamma\":0,\"delta\":0,\"ask\":0,\"strike\":0,\"date\":0,\"yearmonth\":0,\"iv\":0,\"expiry\":0,\"open_interest\":0,\"theta\":0}}","tags":null,"baseRowId":null,"defaultRowCommitVersion":null,"clusteringProvider":null}}
{"add":{"path":"strike_partition=630/symbol=QQQ/part-00000-33837042-f88b-43f9-95f3-51d91f676a58-c000.snappy.parquet","partitionValues":{"symbol":"QQQ","strike_partition":"630"},"size":4980,"modificationTime":1770235377480,"dataChange":true,"stats":"{\"numRecords\":4,\"minValues\":{\"bid\":7.2,\"iv\":-0.0,\"right\":\"CALL\",\"expiry\":\"20260331\",\"last\":6.7,\"gamma\":-0.0,\"ask\":7.3,\"date\":\"2026-02-04\",\"timestamp\":\"2026-02-04T15:02:46.475488Z\",\"theta\":-0.11190224766223622,\"strike\":633.0,\"open_interest\":0,\"yearmonth\":202602,\"delta\":-0.6917840364404851,\"vega\":-0.0,\"volume\":0},\"maxValues\":{\"delta\":0.0,\"last\":36.35,\"expiry\":\"20260331\",\"ask\":36.09,\"right\":\"PUT\",\"theta\":0.0,\"volume\":15,\"vega\":0.85698837766585,\"bid\":34.74,\"open_interest\":0,\"gamma\":0.008514598547769156,\"timestamp\":\"2026-02-04T15:02:50.044113Z\",\"date\":\"2026-02-04\",\"yearmonth\":202602,\"iv\":0.190034124015481,\"strike\":638.0},\"nullCount\":{\"ask\":0,\"theta\":0,\"date\":0,\"yearmonth\":0,\"bid\":0,\"volume\":0,\"expiry\":0,\"gamma\":0,\"vega\":0,\"delta\":0,\"open_interest\":0,\"iv\":0,\"right\":0,\"strike\":0,\"timestamp\":0,\"last\":0}}","tags":null,"baseRowId":null,"defaultRowCommitVersion":null,"clusteringProvider":null}}
{"add":{"path":"strike_partition=560/symbol=QQQ/part-00000-9f398a44-7704-41d3-a3d1-3a280a848ceb-c000.snappy.parquet","partitionValues":{"symbol":"QQQ","strike_partition":"560"},"size":4972,"modificationTime":1770235377480,"dataChange":true,"stats":"{\"numRecords\":4,\"minValues\":{\"timestamp\":\"2026-02-04T15:02:12.865505Z\",\"yearmonth\":202602,\"iv\":-0.0,\"volume\":0,\"delta\":-0.0,\"date\":\"2026-02-04\",\"right\":\"CALL\",\"bid\":7.94,\"open_interest\":0,\"ask\":8.04,\"vega\":-0.0,\"strike\":563.0,\"last\":7.6,\"theta\":-0.2079686234358249,\"expiry\":\"20260331\",\"gamma\":-0.0},\"maxValues\":{\"delta\":0.775079876418975,\"gamma\":0.004828135283225606,\"timestamp\":\"2026-02-04T15:02:16.439735Z\",\"theta\":0.0,\"date\":\"2026-02-04\",\"iv\":0.26664379044824826,\"open_interest\":0,\"right\":\"PUT\",\"yearmonth\":202602,\"strike\":568.0,\"expiry\":\"20260331\",\"vega\":0.6809563745260832,\"ask\":55.54,\"bid\":54.14,\"volume\":175,\"last\":10.35},\"nullCount\":{\"expiry\":0,\"volume\":0,\"gamma\":0,\"ask\":0,\"bid\":0,\"theta\":0,\"strike\":0,\"yearmonth\":0,\"vega\":0,\"last\":0,\"open_interest\":0,\"right\":0,\"date\":0,\"timestamp\":0,\"delta\":0,\"iv\":0}}","tags":null,"baseRowId":null,"defaultRowCommitVersion":null,"clusteringProvider":null}}
{"add":{"path":"strike_partition=600/symbol=QQQ/part-00000-37266c03-d631-4ef2-bfd0-763ba45429e2-c000.snappy.parquet","partitionValues":{"strike_partition":"600","symbol":"QQQ"},"size":4990,"modificationTime":1770235377480,"dataChange":true,"stats":"{\"numRecords\":4,\"minValues\":{\"yearmonth\":202602,\"strike\":603.0,\"right\":\"CALL\",\"last\":17.79,\"volume\":14,\"timestamp\":\"2026-02-04T15:02:32.171821Z\",\"expiry\":\"20260331\",\"theta\":-0.22283736625153594,\"ask\":17.86,\"delta\":-0.0,\"open_interest\":0,\"vega\":-0.0,\"date\":\"2026-02-04\",\"bid\":17.72,\"iv\":-0.0,\"gamma\":-0.0},\"maxValues\":{\"ask\":25.23,\"theta\":0.0,\"delta\":0.5729788617701483,\"open_interest\":0,\"date\":\"2026-02-04\",\"bid\":24.46,\"yearmonth\":202602,\"right\":\"PUT\",\"expiry\":\"20260331\",\"iv\":0.2244012150791336,\"last\":25.0,\"strike\":608.0,\"gamma\":0.0074816904307190785,\"timestamp\":\"2026-02-04T15:02:35.745580Z\",\"vega\":0.923268742491345,\"volume\":116},\"nullCount\":{\"ask\":0,\"bid\":0,\"right\":0,\"volume\":0,\"gamma\":0,\"yearmonth\":0,\"timestamp\":0,\"theta\":0,\"iv\":0,\"last\":0,\"strike\":0,\"delta\":0,\"open_interest\":0,\"date\":0,\"vega\":0,\"expiry\":0}}","tags":null,"baseRowId":null,"defaultRowCommitVersion":null,"clusteringProvider":null}}
{"add":{"path":"strike_partition=580/symbol=QQQ/part-00000-f1ff788f-aa09-4e57-9ac7-5d9d38f0059a-c000.snappy.parquet","partitionValues":{"strike_partition":"580","symbol":"QQQ"},"size":4927,"modificationTime":1770235377480,"dataChange":true,"stats":"{\"numRecords\":4,\"minValues\":{\"volume\":0,\"theta\":-0.0,\"expiry\":\"20260331\",\"strike\":583.0,\"bid\":11.92,\"last\":13.9,\"vega\":-0.0,\"ask\":12.03,\"open_interest\":0,\"date\":\"2026-02-04\",\"gamma\":-0.0,\"right\":\"CALL\",\"yearmonth\":202602,\"timestamp\":\"2026-02-04T15:02:22.407531Z\",\"delta\":-0.0,\"iv\":-0.0},\"maxValues\":{\"delta\":0.0,\"open_interest\":0,\"strike\":588.0,\"expiry\":\"20260331\",\"right\":\"PUT\",\"volume\":23,\"vega\":0.0,\"date\":\"2026-02-04\",\"iv\":0.0,\"yearmonth\":202602,\"timestamp\":\"2026-02-04T15:02:25.978473Z\",\"ask\":39.5,\"last\":14.82,\"gamma\":0.0,\"theta\":0.0,\"bid\":38.11},\"nullCount\":{\"volume\":0,\"iv\":0,\"timestamp\":0,\"delta\":0,\"open_interest\":0,\"ask\":0,\"theta\":0,\"bid\":0,\"gamma\":0,\"expiry\":0,\"right\":0,\"date\":0,\"yearmonth\":0,\"vega\":0,\"strike\":0,\"last\":0}}","tags":null,"baseRowId":null,"defaultRowCommitVersion":null,"clusteringProvider":null}}
{"add":{"path":"strike_partition=640/symbol=QQQ/part-00000-9e2b62f9-2dbd-47d8-8f3a-7ac76a3e0977-c000.snappy.parquet","partitionValues":{"symbol":"QQQ","strike_partition":"640"},"size":5025,"modificationTime":1770235377480,"dataChange":true,"stats":"{\"numRecords\":4,\"minValues\":{\"right\":\"CALL\",\"bid\":4.41,\"theta\":-0.12851829172214213,\"delta\":-0.7863011668948076,\"ask\":4.5,\"last\":4.44,\"vega\":-0.0,\"date\":\"2026-02-04\",\"volume\":0,\"yearmonth\":202602,\"iv\":-0.0,\"expiry\":\"20260331\",\"gamma\":-0.0,\"open_interest\":0,\"timestamp\":\"2026-02-04T15:02:51.233336Z\",\"strike\":643.0},\"maxValues\":{\"volume\":130,\"right\":\"PUT\",\"date\":\"2026-02-04\",\"bid\":41.98,\"strike\":648.0,\"open_interest\":0,\"timestamp\":\"2026-02-04T15:02:54.823672Z\",\"delta\":0.23572244302783918,\"yearmonth\":202602,\"iv\":0.18011236771692574,\"expiry\":\"20260331\",\"gamma\":0.00806054436383637,\"last\":5.79,\"theta\":0.0,\"ask\":43.57,\"vega\":0.6925093779138134},\"nullCount\":{\"date\":0,\"gamma\":0,\"iv\":0,\"last\":0,\"bid\":0,\"yearmonth\":0,\"delta\":0,\"right\":0,\"strike\":0,\"volume\":0,\"open_interest\":0,\"vega\":0,\"ask\":0,\"expiry\":0,\"theta\":0,\"timestamp\":0}}","tags":null,"baseRowId":null,"defaultRowCommitVersion":null,"clusteringProvider":null}}
{"add":{"path":"strike_partition=570/symbol=QQQ/part-00000-ce8ef86b-0c14-472c-9198-43dfdb152e6a-c000.snappy.parquet","partitionValues":{"symbol":"QQQ","strike_partition":"570"},"size":4969,"modificationTime":1770235377481,"dataChange":true,"stats":"{\"numRecords\":4,\"minValues\":{\"gamma\":-0.0,\"open_interest\":0,\"delta\":-0.0,\"strike\":573.0,\"timestamp\":\"2026-02-04T15:02:17.634645Z\",\"expiry\":\"20260331\",\"last\":11.2,\"volume\":0,\"vega\":-0.0,\"yearmonth\":202602,\"bid\":9.73,\"theta\":-0.22238722396863153,\"right\":\"CALL\",\"date\":\"2026-02-04\",\"ask\":9.82,\"iv\":-0.0},\"maxValues\":{\"right\":\"PUT\",\"open_interest\":0,\"delta\":0.7266856241797746,\"last\":11.94,\"iv\":0.2549196077362776,\"vega\":0.7811526099842965,\"volume\":35,\"bid\":45.96,\"ask\":47.27,\"gamma\":0.005591493206715572,\"timestamp\":\"2026-02-04T15:02:21.217999Z\",\"strike\":578.0,\"theta\":0.0,\"expiry\":\"20260331\",\"date\":\"2026-02-04\",\"yearmonth\":202602},\"nullCount\":{\"iv\":0,\"timestamp\":0,\"yearmonth\":0,\"ask\":0,\"strike\":0,\"last\":0,\"bid\":0,\"right\":0,\"expiry\":0,\"theta\":0,\"gamma\":0,\"open_interest\":0,\"date\":0,\"volume\":0,\"vega\":0,\"delta\":0}}","tags":null,"baseRowId":null,"defaultRowCommitVersion":null,"clusteringProvider":null}}
{"add":{"path":"strike_partition=610/symbol=QQQ/part-00000-e16192c7-a6f7-4c32-8805-b208ba760131-c000.snappy.parquet","partitionValues":{"symbol":"QQQ","strike_partition":"610"},"size":5029,"modificationTime":1770235377481,"dataChange":true,"stats":"{\"numRecords\":4,\"minValues\":{\"expiry\":\"20260331\",\"open_interest\":0,\"ask\":15.98,\"right\":\"CALL\",\"bid\":15.85,\"strike\":613.0,\"timestamp\":\"2026-02-04T15:02:36.936201Z\",\"vega\":-0.0,\"volume\":5,\"date\":\"2026-02-04\",\"gamma\":-0.0,\"yearmonth\":202602,\"delta\":-0.5558238455944586,\"last\":14.75,\"theta\":-0.21289522099823088,\"iv\":-0.0},\"maxValues\":{\"vega\":0.9440561406688381,\"expiry\":\"20260331\",\"yearmonth\":202602,\"gamma\":0.008378636953819667,\"ask\":24.46,\"bid\":23.23,\"theta\":0.0,\"timestamp\":\"2026-02-04T15:02:40.517544Z\",\"date\":\"2026-02-04\",\"volume\":49,\"iv\":0.21245429383933886,\"last\":23.84,\"delta\":0.49525344503361163,\"right\":\"PUT\",\"strike\":618.0,\"open_interest\":0},\"nullCount\":{\"strike\":0,\"ask\":0,\"volume\":0,\"expiry\":0,\"gamma\":0,\"vega\":0,\"theta\":0,\"last\":0,\"bid\":0,\"date\":0,\"delta\":0,\"yearmonth\":0,\"right\":0,\"open_interest\":0,\"iv\":0,\"timestamp\":0}}","tags":null,"baseRowId":null,"defaultRowCommitVersion":null,"clusteringProvider":null}}
{"commitInfo":{"timestamp":1770235377481,"operation":"WRITE","operationParameters":{"mode":"Append","partitionBy":"[\"strike_partition\",\"symbol\"]"},"engineInfo":"delta-rs:py-1.3.2","clientVersion":"delta-rs.py-1.3.2","operationMetrics":{"execution_time_ms":7,"num_added_files":10,"num_added_rows":38,"num_partitions":0,"num_removed_files":0}}}